sagellm_gateway/__init__.py
sagellm_gateway/__init__.pyc
sagellm_gateway/__main__.pyc
sagellm_gateway/models.pyc
sagellm_gateway/server.pyc
sagellm_gateway/__pycache__/__init__.cpython-311.pyc
sagellm_gateway/__pycache__/__main__.cpython-311.pyc
sagellm_gateway/__pycache__/models.cpython-311.pyc
sagellm_gateway/__pycache__/server.cpython-311.pyc
sagellm_gateway/adapters/__init__.py
sagellm_gateway/adapters/__init__.pyc
sagellm_gateway/adapters/base.pyc
sagellm_gateway/adapters/sagellm.pyc
sagellm_gateway/adapters/__pycache__/__init__.cpython-311.pyc
sagellm_gateway/adapters/__pycache__/base.cpython-311.pyc
sagellm_gateway/adapters/__pycache__/mock.cpython-311.pyc
sagellm_gateway/adapters/__pycache__/sagellm.cpython-311.pyc
sagellm_gateway/session/__init__.py
sagellm_gateway/session/__init__.pyc
sagellm_gateway/session/manager.pyc
sagellm_gateway/session/storage.pyc
sagellm_gateway/session/__pycache__/__init__.cpython-311.pyc
sagellm_gateway/session/__pycache__/manager.cpython-311.pyc
sagellm_gateway/session/__pycache__/storage.cpython-311.pyc
isagellm_gateway-0.4.0.7.dist-info/METADATA
isagellm_gateway-0.4.0.7.dist-info/WHEEL
isagellm_gateway-0.4.0.7.dist-info/entry_points.txt
isagellm_gateway-0.4.0.7.dist-info/top_level.txt
isagellm_gateway-0.4.0.7.dist-info/RECORD
