Metadata-Version: 2.4
Name: isagellm-gateway
Version: 0.4.0.7
Summary: sageLLM Gateway - OpenAI/Anthropic compatible API Gateway (L6)
Author-email: IntelliStream Team <intellistream@github.com>
License: Apache-2.0
Project-URL: Documentation, https://intellistream.github.io/sagellm-docs/
Project-URL: Homepage, https://github.com/intellistream/sagellm-gateway
Project-URL: Issues, https://github.com/intellistream/sagellm-gateway/issues
Project-URL: Repository, https://github.com/intellistream/sagellm-gateway
Keywords: sagellm,gateway,llm,openai,anthropic,inference
Classifier: Development Status :: 3 - Alpha
Classifier: Intended Audience :: Developers
Classifier: License :: OSI Approved :: Apache Software License
Classifier: Programming Language :: Python :: 3
Classifier: Programming Language :: Python :: 3.10
Classifier: Programming Language :: Python :: 3.11
Classifier: Programming Language :: Python :: 3.12
Classifier: Topic :: Scientific/Engineering :: Artificial Intelligence
Requires-Python: ==3.11.*
Requires-Dist: isagellm-protocol<0.5.0,>=0.4.0.0
Requires-Dist: fastapi<1.0.0,>=0.115.0
Requires-Dist: uvicorn[standard]<1.0.0,>=0.34.0
Requires-Dist: pydantic<3.0.0,>=2.10.0
Requires-Dist: sse-starlette>=1.8.0
Requires-Dist: httpx<1.0.0,>=0.28.0
Provides-Extra: dev
Requires-Dist: pytest>=7.4.0; extra == "dev"
Requires-Dist: pytest-asyncio>=0.21.0; extra == "dev"
Requires-Dist: pytest-cov>=4.1.0; extra == "dev"
Requires-Dist: ruff>=0.4.0; extra == "dev"
Requires-Dist: mypy>=1.7.0; extra == "dev"
Requires-Dist: isage-pypi-publisher>=0.2.0; extra == "dev"
